Workbook

Sheet Read_Me
A1: Field | B1: Guidance
A2: Deliverable | B2: G1_Asset_Criticality_Scoring_Matrix_v1.0 - companion workbook to G1_Asset_Criticality_Framework_v1.0.docx (Operational Sense, Sprint 1).
A3: What it contains | B3: Factors and definitions | scoring scales (the scoring matrix) | parameters (weights, bands, overrides) | classification rules | 10 worked assessments with live formulas | rationale per score | field definitions | hierarchy alignment | source register | review log | open issues.
A4: What criticality means here | B4: Criticality rates the CONSEQUENCE of losing an installed asset (tag-level asset instance). It is not failure likelihood, not asset condition, and not the case-level severity field in the Knowledge Base.
A5: Method in one line | B5: Score 5 factors from 1 to 5, apply proposed weights, convert to a 0-100 index (weighted score x 20), assign Low/Medium/High/Critical by band, then apply safety/environment override floors.
A6: Status | B6: DRAFT PROPOSAL. Weights, bands, default time bands and overrides are team proposals, not agreed standards. They need approval by the relevant workstreams and calibration with a site.
A7: Examples | B7: The 10 assessments use ASSUMED service contexts. They are illustrative, not real plant data. Tags P-101, M-101, C-101 (AST-0001 to AST-0003) match the M03 hierarchy; the other asset IDs are illustrative additions.
A8: How to reproduce | B8: Change only the blue score cells on sheet Assessments (1-5). All other columns are formulas driven by sheet Parameters. Weights must total 100% (check on Parameters).
A9: Colour code | B9: Blue text = input. Black = formula or text. Yellow = key parameter that the team may change after approval.
A10: Hierarchy dependency | B10: Aligned with the DRAFT hierarchy G1_Equipment_Hierarchy_v1.0.xlsx. The approved hierarchy is a dependency; re-check IDs once approved.
A11: Review status | B11: Backend and AI & Retrieval review NOT yet held. See Review_Log.

Sheet Summary
A1: Final category | B1: Assets | C1: Share
A2: Critical | B2: =COUNTIF(Assessments!$S$2:$S$200,A2) -> 3 | C2: =IF($B$6=0,0,B2/$B$6) -> 0.3
A3: High | B3: =COUNTIF(Assessments!$S$2:$S$200,A3) -> 2 | C3: =IF($B$6=0,0,B3/$B$6) -> 0.2
A4: Medium | B4: =COUNTIF(Assessments!$S$2:$S$200,A4) -> 2 | C4: =IF($B$6=0,0,B4/$B$6) -> 0.2
A5: Low | B5: =COUNTIF(Assessments!$S$2:$S$200,A5) -> 3 | C5: =IF($B$6=0,0,B5/$B$6) -> 0.3
A6: TOTAL | B6: =SUM(B2:B5) -> 10 | C6: =SUM(C2:C5) -> 1
A8: Class | B8: Assets | C8: Average index
A9: EQ-PUMP | B9: =COUNTIF(Assessments!$D$2:$D$200,A9) -> 4 | C9: =IF(B9=0,0,AVERAGEIF(Assessments!$D$2:$D$200,A9,Assessments!$M$2:$M$200)) -> 59.25
A10: EQ-MOTOR | B10: =COUNTIF(Assessments!$D$2:$D$200,A10) -> 3 | C10: =IF(B10=0,0,AVERAGEIF(Assessments!$D$2:$D$200,A10,Assessments!$M$2:$M$200)) -> 44.333333
A11: EQ-COMP | B11: =COUNTIF(Assessments!$D$2:$D$200,A11) -> 3 | C11: =IF(B11=0,0,AVERAGEIF(Assessments!$D$2:$D$200,A11,Assessments!$M$2:$M$200)) -> 52.333333
A13: Assets where an override changed the category | B13: =COUNTIF(Assessments!$T$2:$T$200,"Yes") -> 1
A14: Weights check | B14: =Parameters!B8 -> OK

Sheet Factors_Definitions
A1: factor_id | B1: factor_name | C1: definition | D1: measurable indicators | E1: weight (from Parameters) | F1: weight basis
A2: F1 | B2: Safety (personnel and equipment) | C2: Worst credible harm to people, and damage to the asset or neighbouring equipment, if the asset fails. | D2: Worst credible injury outcome; potential for fire, explosion, pressure or stored-energy release; damage to adjacent equipment; loss of a safety function. | E2: =Parameters!B2 -> 0.3 | F2: Team proposal; see framework document Section 4.
A3: F2 | B3: Production loss and downtime | C3: Loss of output caused by the asset failing, considering duration and scope of the interruption with no workaround. | D3: Duration of interruption; scope (one machine, a line, the whole plant); whether lost output can be recovered. | E3: =Parameters!B3 -> 0.25 | F3: Team proposal; see framework document Section 4.
A4: F3 | B4: Environmental impact | C4: Harm to the environment, and any regulatory consequence, if the asset fails. | D4: Type and amount of release; whether it stays inside containment; whether it must be reported to a regulator. | E4: =Parameters!B4 -> 0.15 | F4: Team proposal; see framework document Section 4.
A5: F4 | B5: Operational dependency and business continuity | C5: How much other processes or services depend on the asset, and whether a standby or workaround exists. | D5: Installed standby or redundancy; number of dependent processes or services; availability of a workaround; single point of failure. | E5: =Parameters!B5 -> 0.15 | F5: Team proposal; see framework document Section 4.
A6: F5 | B6: Maintenance and repair consequences | C6: Effort, time and cost needed to restore the asset after a failure. | D6: Repair duration; spares availability and lead time; repair cost relative to the site maintenance budget; need for specialist resources. | E6: =Parameters!B6 -> 0.15 | F6: Team proposal; see framework document Section 4.

Sheet Scoring_Scales
A1: factor_id | B1: factor | C1: 1 - Very low | D1: 2 - Low | E1: 3 - Moderate | F1: 4 - High | G1: 5 - Very high
A2: F1 | B2: Safety (personnel and equipment) | C2: No credible injury; no effect on other equipment. | D2: First-aid injury possible; minor damage limited to the asset itself. | E2: Medical-treatment injury possible; moderate damage to connected equipment. | F2: Lost-time or serious injury possible; significant damage to adjacent equipment or loss of a safety function. | G2: Fatality or permanently disabling injury possible; credible fire, explosion or major energy/pressure release.
A3: F2 | B3: Production loss and downtime | C3: No production effect. | D3: Reduced rate, or interruption of under about 4 hours on one machine or line section; fully recoverable. | E3: Interruption of about 4 to 24 hours on a line; partly recoverable. | F3: Line stopped for about 1 to 3 days, or a short plant-wide stop. | G3: Line stopped for more than about 3 days, or a prolonged plant-wide stop; output not recoverable.
A4: F3 | B4: Environmental impact | C4: No release or emission. | D4: Minor release, contained on site and cleaned up by routine action; no reporting. | E4: Release needing formal clean-up and internal incident reporting. | F4: Release beyond local containment, or reportable to a regulator; localised effect. | G4: Major or off-site release, significant regulatory action or lasting environmental damage.
A5: F4 | B5: Operational dependency and business continuity | C5: Installed standby with automatic changeover; no dependency. | D5: Standby available with manual changeover, or few dependents with an easy workaround. | E5: Partial backup or buffer capacity covers a short outage; limited dependents. | F5: No standby; several downstream processes depend on it; workaround difficult. | G5: Single point of failure for the plant or a critical service; no workaround.
A6: F5 | B6: Maintenance and repair consequences | C6: Simple repair within about 4 hours; stock spares; low cost; in-house skills. | D6: Repair within a shift; spares in stock; routine skills; low to moderate cost. | E6: Repair takes 1 to 2 days; spares from supplier within days; moderate cost. | F6: Repair takes several days to weeks; long-lead spares or specialist contractor; high cost. | G6: Repair takes weeks to months; OEM-only or custom parts; replacement likely; very high cost.
A8: Note | B8: Time bands (F2, F5) are PROPOSED DEFAULTS and must be calibrated by the site. Score the worst credible consequence of losing the asset's function in normal operation, counting only standby, protection and workarounds that actually exist. If unsure between two levels, choose the higher one and record why.

Sheet Parameters
A1: Parameter | B1: Value | C1: Note
A2: Weight - F1 Safety | B2: 0.3 | C2: Proposed. Highest weight: safety harm is not recoverable.
A3: Weight - F2 Production loss and downtime | B3: 0.25 | C3: Proposed.
A4: Weight - F3 Environmental impact | B4: 0.15 | C4: Proposed.
A5: Weight - F4 Operational dependency and continuity | B5: 0.15 | C5: Proposed.
A6: Weight - F5 Maintenance and repair consequences | B6: 0.15 | C6: Proposed.
A7: Total weight | B7: =SUM(B2:B6) -> 1 | C7: Must equal 100%.
A8: Weights check | B8: =IF(ROUND(B7,4)=1,"OK","ERROR: weights must total 100%") -> OK
A10: Band threshold - Critical (index >=) | B10: 80 | C10: Equals weighted score 4.0.
A11: Band threshold - High (index >=) | B11: 60 | C11: Equals weighted score 3.0.
A12: Band threshold - Medium (index >=) | B12: 40 | C12: Equals weighted score 2.0. Below this = Low.
A14: Override R1 - Safety score >= (forces Critical) | B14: 5 | C14: Proposed.
A15: Override R2 - Environmental score >= (forces Critical) | B15: 5 | C15: Proposed.
A16: Override R3 - Safety score >= (minimum High) | B16: 4 | C16: Proposed.
A17: Override R4 - Environmental score >= (minimum High) | B17: 4 | C17: Proposed.

Sheet Classification_Rules
A1: A. Category bands (applied to the criticality index, rounded to 1 decimal)
A2: Category | B2: Index range | C2: Equivalent weighted score | D2: Meaning | E2: Suggested use (proposal, not a maintenance policy)
A3: Critical | B3: 80.0 to 100.0 | C3: 4.0 to 5.0 | D3: Failure has severe consequences for people, environment, production or continuity. | E3: Highest priority for condition monitoring, spares review and preventive-maintenance review.
A4: High | B4: 60.0 to 79.9 | C4: 3.0 to 3.99 | D4: Failure has major consequences. | E4: Scheduled preventive maintenance and routine monitoring.
A5: Medium | B5: 40.0 to 59.9 | C5: 2.0 to 2.99 | D5: Failure has moderate consequences. | E5: Standard preventive maintenance.
A6: Low | B6: 20.0 to 39.9 | C6: 1.0 to 1.99 | D6: Failure has limited consequences. | E6: Basic checks; run-to-failure may be acceptable where spares are easy to get.
A8: B. Override rules (final category = the higher of the band category and the override floor)
A9: Rule | B9: Condition | C9: Effect | D9: Reason
A10: R1 | B10: Safety score >= 5 | C10: Final category = Critical | D10: A credible fatality or major release must not be diluted by low scores elsewhere.
A11: R2 | B11: Environmental score >= 5 | C11: Final category = Critical | D11: A major or off-site release must not be diluted.
A12: R3 | B12: Safety score >= 4 | C12: Final category at least High | D12: Serious-injury potential must not fall below High.
A13: R4 | B13: Environmental score >= 4 | C13: Final category at least High | D13: Reportable release potential must not fall below High.
A15: C. Assignment procedure
A16: Step | B16: Action
A17: 1 | B17: Identify the asset instance (asset_id, tag, type) and describe its service and any standby or dependants.
A18: 2 | B18: Score each of the 5 factors from 1 to 5 using sheet Scoring_Scales; write a short rationale for each score (mandatory for scores of 4 or 5).
A19: 3 | B19: Weighted score = sum of (factor score x weight).
A20: 4 | B20: Criticality index = weighted score x 20 (range 20 to 100).
A21: 5 | B21: Assign the band category from the index.
A22: 6 | B22: Apply override rules R1 to R4; final category = higher of band and floor.
A23: 7 | B23: Record assessor, date, status and versions; have operations, safety and maintenance review before approval.
A25: D. Boundary, ties and reassessment
A26: Topic | B26: Rule
A27: Boundaries | B27: Thresholds apply to the index rounded to 1 decimal. An index of exactly 60.0 is High; exactly 80.0 is Critical; exactly 40.0 is Medium.
A28: Uncertain scores | B28: Choose the higher level and record why; do not average two levels.
A29: Driver and driven equipment | B29: Score each asset on its own consequences. A motor or coupling serving a driven machine normally shares the production and dependency scores of that machine.
A30: Reassessment | B30: At least every 12 months (proposed), and after a process change, a change in standby or redundancy, a serious incident, or a change in weights or bands.
A31: Inflation check | B31: If most assets land in Critical or High, review scale use; the method must differentiate.

Sheet Assessments
A1: assessment_id | B1: asset_id | C1: equipment_tag | D1: class_id | E1: type_id | F1: service_context (ASSUMED) | G1: score_safety | H1: score_production | I1: score_environment | J1: score_dependency | K1: score_maintenance | L1: weighted_score | M1: criticality_index | N1: band_rank | O1: band_category | P1: override_floor_rank | Q1: override_rules_triggered | R1: final_rank | S1: final_category | T1: override_changed_category | U1: data_origin
A2: CRA-0001 | B2: AST-0001 | C2: P-101 | D2: EQ-PUMP | E2: TY-PUMP-CENT | F2: Cooling-water circulation pump; single duty, no installed standby; serves the main process line | G2: 3 | H2: 4 | I2: 2 | J2: 4 | K2: 2 | L2: =ROUND(G2*Parameters!$B$2+H2*Parameters!$B$3+I2*Parameters!$B$4+J2*Parameters!$B$5+K2*Parameters!$B$6,2) -> 3.1 | M2: =ROUND(L2/5*100,1) -> 62 | N2: =IF(M2>=Parameters!$B$10,4,IF(M2>=Parameters!$B$11,3,IF(M2>=Parameters!$B$12,2,1))) -> 3 | O2: =CHOOSE(N2,"Low","Medium","High","Critical") -> High | P2: =MAX(IF(G2>=Parameters!$B$14,4,0),IF(I2>=Parameters!$B$15,4,0),IF(G2>=Parameters!$B$16,3,0),IF(I2>=Parameters!$B$17,3,0)) -> 0 | Q2: =IF(TRIM(IF(G2>=Parameters!$B$14,"R1 ","")&IF(I2>=Parameters!$B$15,"R2 ","")&IF(G2>=Parameters!$B$16,"R3 ","")&IF(I2>=Parameters!$B$17,"R4",""))="","None",TRIM(IF(G2>=Parameters!$B$14,"R1 ","")&IF(I2>=Parameters!$B$15,"R2 ","")&IF(G2>=Parameters!$B$16,"R3 ","")&IF(I2>=Parameters!$B$17,"R4",""))) -> None | R2: =MAX(N2,P2) -> 3 | S2: =CHOOSE(R2,"Low","Medium","High","Critical") -> High | T2: =IF(R2>N2,"Yes","No") -> No | U2: Synthetic Scenario
A3: CRA-0002 | B3: AST-0004 | C3: P-102 | D3: EQ-PUMP | E3: TY-PUMP-CENT | F3: Boiler feed-water pump; no installed spare | G3: 5 | H3: 5 | I3: 2 | J3: 5 | K3: 4 | L3: =ROUND(G3*Parameters!$B$2+H3*Parameters!$B$3+I3*Parameters!$B$4+J3*Parameters!$B$5+K3*Parameters!$B$6,2) -> 4.4 | M3: =ROUND(L3/5*100,1) -> 88 | N3: =IF(M3>=Parameters!$B$10,4,IF(M3>=Parameters!$B$11,3,IF(M3>=Parameters!$B$12,2,1))) -> 4 | O3: =CHOOSE(N3,"Low","Medium","High","Critical") -> Critical | P3: =MAX(IF(G3>=Parameters!$B$14,4,0),IF(I3>=Parameters!$B$15,4,0),IF(G3>=Parameters!$B$16,3,0),IF(I3>=Parameters!$B$17,3,0)) -> 4 | Q3: =IF(TRIM(IF(G3>=Parameters!$B$14,"R1 ","")&IF(I3>=Parameters!$B$15,"R2 ","")&IF(G3>=Parameters!$B$16,"R3 ","")&IF(I3>=Parameters!$B$17,"R4",""))="","None",TRIM(IF(G3>=Parameters!$B$14,"R1 ","")&IF(I3>=Parameters!$B$15,"R2 ","")&IF(G3>=Parameters!$B$16,"R3 ","")&IF(I3>=Parameters!$B$17,"R4",""))) -> R1 R3 | R3: =MAX(N3,P3) -> 4 | S3: =CHOOSE(R3,"Low","Medium","High","Critical") -> Critical | T3: =IF(R3>N3,"Yes","No") -> No | U3: Synthetic Scenario
A4: CRA-0003 | B4: AST-0007 | C4: P-201 | D4: EQ-PUMP | E4: TY-PUMP-CENT | F4: Sump drainage pump; installed standby with automatic changeover | G4: 1 | H4: 1 | I4: 2 | J4: 1 | K4: 1 | L4: =ROUND(G4*Parameters!$B$2+H4*Parameters!$B$3+I4*Parameters!$B$4+J4*Parameters!$B$5+K4*Parameters!$B$6,2) -> 1.15 | M4: =ROUND(L4/5*100,1) -> 23 | N4: =IF(M4>=Parameters!$B$10,4,IF(M4>=Parameters!$B$11,3,IF(M4>=Parameters!$B$12,2,1))) -> 1 | O4: =CHOOSE(N4,"Low","Medium","High","Critical") -> Low | P4: =MAX(IF(G4>=Parameters!$B$14,4,0),IF(I4>=Parameters!$B$15,4,0),IF(G4>=Parameters!$B$16,3,0),IF(I4>=Parameters!$B$17,3,0)) -> 0 | Q4: =IF(TRIM(IF(G4>=Parameters!$B$14,"R1 ","")&IF(I4>=Parameters!$B$15,"R2 ","")&IF(G4>=Parameters!$B$16,"R3 ","")&IF(I4>=Parameters!$B$17,"R4",""))="","None",TRIM(IF(G4>=Parameters!$B$14,"R1 ","")&IF(I4>=Parameters!$B$15,"R2 ","")&IF(G4>=Parameters!$B$16,"R3 ","")&IF(I4>=Parameters!$B$17,"R4",""))) -> None | R4: =MAX(N4,P4) -> 1 | S4: =CHOOSE(R4,"Low","Medium","High","Critical") -> Low | T4: =IF(R4>N4,"Yes","No") -> No | U4: Synthetic Scenario
A5: CRA-0004 | B5: AST-0012 | C5: P-305 | D5: EQ-PUMP | E5: TY-PUMP-CENT | F5: Transfer pump for flammable solvent; standby installed; bunded area | G5: 5 | H5: 2 | I5: 4 | J5: 2 | K5: 2 | L5: =ROUND(G5*Parameters!$B$2+H5*Parameters!$B$3+I5*Parameters!$B$4+J5*Parameters!$B$5+K5*Parameters!$B$6,2) -> 3.2 | M5: =ROUND(L5/5*100,1) -> 64 | N5: =IF(M5>=Parameters!$B$10,4,IF(M5>=Parameters!$B$11,3,IF(M5>=Parameters!$B$12,2,1))) -> 3 | O5: =CHOOSE(N5,"Low","Medium","High","Critical") -> High | P5: =MAX(IF(G5>=Parameters!$B$14,4,0),IF(I5>=Parameters!$B$15,4,0),IF(G5>=Parameters!$B$16,3,0),IF(I5>=Parameters!$B$17,3,0)) -> 4 | Q5: =IF(TRIM(IF(G5>=Parameters!$B$14,"R1 ","")&IF(I5>=Parameters!$B$15,"R2 ","")&IF(G5>=Parameters!$B$16,"R3 ","")&IF(I5>=Parameters!$B$17,"R4",""))="","None",TRIM(IF(G5>=Parameters!$B$14,"R1 ","")&IF(I5>=Parameters!$B$15,"R2 ","")&IF(G5>=Parameters!$B$16,"R3 ","")&IF(I5>=Parameters!$B$17,"R4",""))) -> R1 R3 R4 | R5: =MAX(N5,P5) -> 4 | S5: =CHOOSE(R5,"Low","Medium","High","Critical") -> Critical | T5: =IF(R5>N5,"Yes","No") -> Yes | U5: Synthetic Scenario
A6: CRA-0005 | B6: AST-0002 | C6: M-101 | D6: EQ-MOTOR | E6: TY-MOTOR-IM3 | F6: Drive motor of P-101 (same cooling-water duty) | G6: 3 | H6: 4 | I6: 1 | J6: 4 | K6: 3 | L6: =ROUND(G6*Parameters!$B$2+H6*Parameters!$B$3+I6*Parameters!$B$4+J6*Parameters!$B$5+K6*Parameters!$B$6,2) -> 3.1 | M6: =ROUND(L6/5*100,1) -> 62 | N6: =IF(M6>=Parameters!$B$10,4,IF(M6>=Parameters!$B$11,3,IF(M6>=Parameters!$B$12,2,1))) -> 3 | O6: =CHOOSE(N6,"Low","Medium","High","Critical") -> High | P6: =MAX(IF(G6>=Parameters!$B$14,4,0),IF(I6>=Parameters!$B$15,4,0),IF(G6>=Parameters!$B$16,3,0),IF(I6>=Parameters!$B$17,3,0)) -> 0 | Q6: =IF(TRIM(IF(G6>=Parameters!$B$14,"R1 ","")&IF(I6>=Parameters!$B$15,"R2 ","")&IF(G6>=Parameters!$B$16,"R3 ","")&IF(I6>=Parameters!$B$17,"R4",""))="","None",TRIM(IF(G6>=Parameters!$B$14,"R1 ","")&IF(I6>=Parameters!$B$15,"R2 ","")&IF(G6>=Parameters!$B$16,"R3 ","")&IF(I6>=Parameters!$B$17,"R4",""))) -> None | R6: =MAX(N6,P6) -> 3 | S6: =CHOOSE(R6,"Low","Medium","High","Critical") -> High | T6: =IF(R6>N6,"Yes","No") -> No | U6: Synthetic Scenario
A7: CRA-0006 | B7: AST-0008 | C7: M-301 | D7: EQ-MOTOR | E7: TY-MOTOR-IM3 | F7: Conveyor drive motor on a single line; spare motor held in store | G7: 3 | H7: 3 | I7: 1 | J7: 3 | K7: 2 | L7: =ROUND(G7*Parameters!$B$2+H7*Parameters!$B$3+I7*Parameters!$B$4+J7*Parameters!$B$5+K7*Parameters!$B$6,2) -> 2.55 | M7: =ROUND(L7/5*100,1) -> 51 | N7: =IF(M7>=Parameters!$B$10,4,IF(M7>=Parameters!$B$11,3,IF(M7>=Parameters!$B$12,2,1))) -> 2 | O7: =CHOOSE(N7,"Low","Medium","High","Critical") -> Medium | P7: =MAX(IF(G7>=Parameters!$B$14,4,0),IF(I7>=Parameters!$B$15,4,0),IF(G7>=Parameters!$B$16,3,0),IF(I7>=Parameters!$B$17,3,0)) -> 0 | Q7: =IF(TRIM(IF(G7>=Parameters!$B$14,"R1 ","")&IF(I7>=Parameters!$B$15,"R2 ","")&IF(G7>=Parameters!$B$16,"R3 ","")&IF(I7>=Parameters!$B$17,"R4",""))="","None",TRIM(IF(G7>=Parameters!$B$14,"R1 ","")&IF(I7>=Parameters!$B$15,"R2 ","")&IF(G7>=Parameters!$B$16,"R3 ","")&IF(I7>=Parameters!$B$17,"R4",""))) -> None | R7: =MAX(N7,P7) -> 2 | S7: =CHOOSE(R7,"Low","Medium","High","Critical") -> Medium | T7: =IF(R7>N7,"Yes","No") -> No | U7: Synthetic Scenario
A8: CRA-0007 | B8: AST-0009 | C8: M-402 | D8: EQ-MOTOR | E8: TY-MOTOR-IM3 | F8: Workshop ventilation fan motor, general area | G8: 1 | H8: 1 | I8: 1 | J8: 1 | K8: 1 | L8: =ROUND(G8*Parameters!$B$2+H8*Parameters!$B$3+I8*Parameters!$B$4+J8*Parameters!$B$5+K8*Parameters!$B$6,2) -> 1 | M8: =ROUND(L8/5*100,1) -> 20 | N8: =IF(M8>=Parameters!$B$10,4,IF(M8>=Parameters!$B$11,3,IF(M8>=Parameters!$B$12,2,1))) -> 1 | O8: =CHOOSE(N8,"Low","Medium","High","Critical") -> Low | P8: =MAX(IF(G8>=Parameters!$B$14,4,0),IF(I8>=Parameters!$B$15,4,0),IF(G8>=Parameters!$B$16,3,0),IF(I8>=Parameters!$B$17,3,0)) -> 0 | Q8: =IF(TRIM(IF(G8>=Parameters!$B$14,"R1 ","")&IF(I8>=Parameters!$B$15,"R2 ","")&IF(G8>=Parameters!$B$16,"R3 ","")&IF(I8>=Parameters!$B$17,"R4",""))="","None",TRIM(IF(G8>=Parameters!$B$14,"R1 ","")&IF(I8>=Parameters!$B$15,"R2 ","")&IF(G8>=Parameters!$B$16,"R3 ","")&IF(I8>=Parameters!$B$17,"R4",""))) -> None | R8: =MAX(N8,P8) -> 1 | S8: =CHOOSE(R8,"Low","Medium","High","Critical") -> Low | T8: =IF(R8>N8,"Yes","No") -> No | U8: Synthetic Scenario
A9: CRA-0008 | B9: AST-0003 | C9: C-101 | D9: EQ-COMP | E9: TY-COMP-SCREW | F9: Instrument-air compressor; single unit; plant instruments depend on it | G9: 4 | H9: 5 | I9: 2 | J9: 5 | K9: 4 | L9: =ROUND(G9*Parameters!$B$2+H9*Parameters!$B$3+I9*Parameters!$B$4+J9*Parameters!$B$5+K9*Parameters!$B$6,2) -> 4.1 | M9: =ROUND(L9/5*100,1) -> 82 | N9: =IF(M9>=Parameters!$B$10,4,IF(M9>=Parameters!$B$11,3,IF(M9>=Parameters!$B$12,2,1))) -> 4 | O9: =CHOOSE(N9,"Low","Medium","High","Critical") -> Critical | P9: =MAX(IF(G9>=Parameters!$B$14,4,0),IF(I9>=Parameters!$B$15,4,0),IF(G9>=Parameters!$B$16,3,0),IF(I9>=Parameters!$B$17,3,0)) -> 3 | Q9: =IF(TRIM(IF(G9>=Parameters!$B$14,"R1 ","")&IF(I9>=Parameters!$B$15,"R2 ","")&IF(G9>=Parameters!$B$16,"R3 ","")&IF(I9>=Parameters!$B$17,"R4",""))="","None",TRIM(IF(G9>=Parameters!$B$14,"R1 ","")&IF(I9>=Parameters!$B$15,"R2 ","")&IF(G9>=Parameters!$B$16,"R3 ","")&IF(I9>=Parameters!$B$17,"R4",""))) -> R3 | R9: =MAX(N9,P9) -> 4 | S9: =CHOOSE(R9,"Low","Medium","High","Critical") -> Critical | T9: =IF(R9>N9,"Yes","No") -> No | U9: Synthetic Scenario
A10: CRA-0009 | B10: AST-0010 | C10: C-102 | D10: EQ-COMP | E10: TY-COMP-SCREW | F10: General-service plant-air compressor; duty/standby pair | G10: 2 | H10: 2 | I10: 2 | J10: 2 | K10: 3 | L10: =ROUND(G10*Parameters!$B$2+H10*Parameters!$B$3+I10*Parameters!$B$4+J10*Parameters!$B$5+K10*Parameters!$B$6,2) -> 2.15 | M10: =ROUND(L10/5*100,1) -> 43 | N10: =IF(M10>=Parameters!$B$10,4,IF(M10>=Parameters!$B$11,3,IF(M10>=Parameters!$B$12,2,1))) -> 2 | O10: =CHOOSE(N10,"Low","Medium","High","Critical") -> Medium | P10: =MAX(IF(G10>=Parameters!$B$14,4,0),IF(I10>=Parameters!$B$15,4,0),IF(G10>=Parameters!$B$16,3,0),IF(I10>=Parameters!$B$17,3,0)) -> 0 | Q10: =IF(TRIM(IF(G10>=Parameters!$B$14,"R1 ","")&IF(I10>=Parameters!$B$15,"R2 ","")&IF(G10>=Parameters!$B$16,"R3 ","")&IF(I10>=Parameters!$B$17,"R4",""))="","None",TRIM(IF(G10>=Parameters!$B$14,"R1 ","")&IF(I10>=Parameters!$B$15,"R2 ","")&IF(G10>=Parameters!$B$16,"R3 ","")&IF(I10>=Parameters!$B$17,"R4",""))) -> None | R10: =MAX(N10,P10) -> 2 | S10: =CHOOSE(R10,"Low","Medium","High","Critical") -> Medium | T10: =IF(R10>N10,"Yes","No") -> No | U10: Synthetic Scenario
A11: CRA-0010 | B11: AST-0011 | C11: C-201 | D11: EQ-COMP | E11: TY-COMP-SCREW | F11: Workshop compressor for intermittent tool use | G11: 2 | H11: 1 | I11: 2 | J11: 1 | K11: 2 | L11: =ROUND(G11*Parameters!$B$2+H11*Parameters!$B$3+I11*Parameters!$B$4+J11*Parameters!$B$5+K11*Parameters!$B$6,2) -> 1.6 | M11: =ROUND(L11/5*100,1) -> 32 | N11: =IF(M11>=Parameters!$B$10,4,IF(M11>=Parameters!$B$11,3,IF(M11>=Parameters!$B$12,2,1))) -> 1 | O11: =CHOOSE(N11,"Low","Medium","High","Critical") -> Low | P11: =MAX(IF(G11>=Parameters!$B$14,4,0),IF(I11>=Parameters!$B$15,4,0),IF(G11>=Parameters!$B$16,3,0),IF(I11>=Parameters!$B$17,3,0)) -> 0 | Q11: =IF(TRIM(IF(G11>=Parameters!$B$14,"R1 ","")&IF(I11>=Parameters!$B$15,"R2 ","")&IF(G11>=Parameters!$B$16,"R3 ","")&IF(I11>=Parameters!$B$17,"R4",""))="","None",TRIM(IF(G11>=Parameters!$B$14,"R1 ","")&IF(I11>=Parameters!$B$15,"R2 ","")&IF(G11>=Parameters!$B$16,"R3 ","")&IF(I11>=Parameters!$B$17,"R4",""))) -> None | R11: =MAX(N11,P11) -> 1 | S11: =CHOOSE(R11,"Low","Medium","High","Critical") -> Low | T11: =IF(R11>N11,"Yes","No") -> No | U11: Synthetic Scenario

Sheet Example_Rationale
A1: assessment_id | B1: asset_id | C1: factor | D1: score | E1: rationale (assumed context)
A2: CRA-0001 | B2: AST-0001 | C2: F1 Safety (personnel and equipment) | D2: 3 | E2: Loss of cooling can overheat connected equipment; hot-surface injury potential is moderate.
A3: CRA-0001 | B3: AST-0001 | C3: F2 Production loss and downtime | D3: 4 | E3: Cooling loss forces a line stop; restart and recovery assumed to take more than a day.
A4: CRA-0001 | B4: AST-0001 | C4: F3 Environmental impact | D4: 2 | E4: Water leakage is minor and drains on site.
A5: CRA-0001 | B5: AST-0001 | C5: F4 Operational dependency and business continuity | D5: 4 | E5: No standby; several users share the cooling loop.
A6: CRA-0001 | B6: AST-0001 | C6: F5 Maintenance and repair consequences | D6: 2 | E6: Routine centrifugal pump repair; spares assumed in stock.
A7: CRA-0002 | B7: AST-0004 | C7: F1 Safety (personnel and equipment) | D7: 5 | E7: Loss of feed water can lead to low boiler level, a credible pressure-equipment hazard (assumed site context).
A8: CRA-0002 | B8: AST-0004 | C8: F2 Production loss and downtime | D8: 5 | E8: Loss of steam supply stops the plant; prolonged outage if the boiler is damaged.
A9: CRA-0002 | B9: AST-0004 | C9: F3 Environmental impact | D9: 2 | E9: Hot-water release is minor and contained.
A10: CRA-0002 | B10: AST-0004 | C10: F4 Operational dependency and business continuity | D10: 5 | E10: Sole feed to steam supply; no workaround.
A11: CRA-0002 | B11: AST-0004 | C11: F5 Maintenance and repair consequences | D11: 4 | E11: High-pressure multistage pump; long-lead spares and specialist repair assumed.
A12: CRA-0003 | B12: AST-0007 | C12: F1 Safety (personnel and equipment) | D12: 1 | E12: No credible injury from failure.
A13: CRA-0003 | B13: AST-0007 | C13: F2 Production loss and downtime | D13: 1 | E13: Standby takes over; no production effect.
... A51: CRA-0010 | B51: AST-0011 | C51: F5 Maintenance and repair consequences | D51: 2 | E51: Repair within a shift.

Sheet Field_Definitions
A1: field_name | B1: description | C1: suggested data type | D1: mandatory / optional | E1: allowed values / range | F1: source | G1: example | H1: integration note
A2: assessment_id | B2: Unique ID of one assessment record. | C2: VARCHAR(20), PK | D2: Mandatory | E2: Format CRA-nnnn | F2: Input | G2: CRA-0001 | H2: Primary key of the assessment table.
A3: asset_id | B3: Installed asset assessed. | C3: VARCHAR, FK to Asset_Instance.asset_id | D3: Mandatory | E3: Existing AST- ID | F3: Input | G3: AST-0001 | H3: Criticality attaches to the asset instance, not to the equipment type or a case.
A4: equipment_tag | B4: Plant tag of the asset. | C4: VARCHAR | D4: Optional | E4: Free text | F4: Input / lookup | G4: P-101 | H4: Denormalised for readability; source of truth is the asset table.
A5: class_id | B5: Equipment class of the asset. | C5: VARCHAR, FK to Equipment_Class | D5: Mandatory | E5: EQ-PUMP, EQ-MOTOR, EQ-COMP | F5: Lookup from type | G5: EQ-PUMP | H5: Enables filtering by class; must match the asset's type.
A6: type_id | B6: Equipment type of the asset. | C6: VARCHAR, FK to Equipment_Type | D6: Mandatory | E6: TY- ID | F6: Lookup from asset | G6: TY-PUMP-CENT | H6: Links the assessment to the approved hierarchy.
A7: service_context | B7: Short description of duty, standby and dependants used when scoring. | C7: TEXT | D7: Mandatory | E7: Free text | F7: Input | G7: Cooling-water pump, no standby | H7: Required so another assessor can reproduce the scores.
A8: assessment_date | B8: Date the assessment was made. | C8: DATE | D8: Mandatory | E8: Valid date | F8: Input | G8: 2026-10-25 | H8: Used with is_current to pick the latest assessment.
A9: assessor_name | B9: Person who scored the asset. | C9: VARCHAR | D9: Mandatory | E9: Free text | F9: Input | G9: (name) | H9: Illustrative examples carry no assessor.
A10: reviewer_name | B10: Person who reviewed the scores. | C10: VARCHAR | D10: Optional until status = Reviewed | E10: Free text | F10: Input | G10: (name) | H10: Needed before approval.
A11: framework_version | B11: Version of this framework used. | C11: VARCHAR(10) | D11: Mandatory | E11: e.g. v1.0 | F11: Input | G11: v1.0 | H11: Supports reproducibility when the framework changes.
A12: weights_version | B12: Version of the weight set used. | C12: VARCHAR(10) | D12: Mandatory | E12: e.g. W1.0 | F12: Input | G12: W1.0 | H12: Store weights in a parameter table keyed by this value.
A13: score_safety | B13: Factor F1 score. | C13: SMALLINT, CHECK 1-5 | D13: Mandatory | E13: 1 to 5 | F13: Input | G13: 3
A14: score_production | B14: Factor F2 score. | C14: SMALLINT, CHECK 1-5 | D14: Mandatory | E14: 1 to 5 | F14: Input | G14: 4
A15: score_environment | B15: Factor F3 score. | C15: SMALLINT, CHECK 1-5 | D15: Mandatory | E15: 1 to 5 | F15: Input | G15: 2
A16: score_dependency | B16: Factor F4 score. | C16: SMALLINT, CHECK 1-5 | D16: Mandatory | E16: 1 to 5 | F16: Input | G16: 4
A17: score_maintenance | B17: Factor F5 score. | C17: SMALLINT, CHECK 1-5 | D17: Mandatory | E17: 1 to 5 | F17: Input | G17: 2
A18: rationale_safety / _production / _environment / _dependency / _maintenance | B18: Reason for each score (five text fields). | C18: TEXT | D18: Mandatory when the score is 4 or 5; otherwise recommended | E18: Free text | F18: Input | G18: Loss of cooling forces a line stop | H18: Gives auditability. Optional extra context for retrieval.
A19: weighted_score | B19: Sum of score x weight. | C19: NUMERIC(3,2) | D19: Calculated | E19: 1.00 to 5.00 | F19: Calculated | G19: 3.10 | H19: Compute in the database or application; do not type by hand.
A20: criticality_index | B20: Weighted score x 20. | C20: NUMERIC(4,1) | D20: Calculated | E20: 20.0 to 100.0 | F20: Calculated | G20: 62.0 | H20: Main numeric filter and ranking value.
A21: band_category | B21: Category from the index bands before overrides. | C21: VARCHAR enum | D21: Calculated | E21: Low, Medium, High, Critical | F21: Calculated | G21: High
A22: override_rules_triggered | B22: Override rules that apply (R1 to R4). | C22: VARCHAR | D22: Calculated | E22: R1..R4 or None | F22: Calculated | G22: R1 R3 | H22: Several rules can apply at once.
A23: final_category | B23: Category after overrides. | C23: VARCHAR enum | D23: Calculated, mandatory | E23: Low, Medium, High, Critical | F23: Calculated | G23: High | H23: The value used by other modules.
A24: override_changed_category | B24: Whether an override raised the category. | C24: BOOLEAN | D24: Calculated | E24: Yes / No | F24: Calculated | G24: No | H24: Useful for QA of override rules.
A25: assessment_status | B25: Workflow status. | C25: VARCHAR enum | D25: Mandatory | E25: Draft, Reviewed, Approved, Superseded | F25: Input | G25: Draft | H25: Only Approved assessments are treated as current.
A26: data_origin | B26: How the record was produced. | C26: VARCHAR enum | D26: Mandatory | E26: Synthetic Scenario, Site Assessment | F26: Input | G26: Synthetic Scenario | H26: Aligned with the KB 'Case Origin' wording; never label assumed examples as site data.
A27: is_current | B27: Marks the latest approved assessment of the asset. | C27: BOOLEAN | D27: Mandatory | E27: TRUE / FALSE | F27: Input / system | G27: TRUE | H27: At most one TRUE per asset_id.
A28: next_review_date | B28: When the asset must be reassessed. | C28: DATE | D28: Optional | E28: Valid date | F28: Input | G28: 2027-10-25 | H28: Proposal: 12 months after assessment_date.
A29: notes | B29: Other remarks. | C29: TEXT | D29: Optional | E29: Free text | F29: Input

Sheet Hierarchy_Alignment
A1: Topic | B1: Alignment note
A2: Level of criticality | B2: Installed asset instance (AST- ID, e.g. P-101). Equipment type and class are inherited for filtering.
A3: Link keys | B3: asset_id -> Asset_Instance; type_id -> Equipment_Type (TY-); class_id -> Equipment_Class (EQ-). IDs follow G1_Equipment_Hierarchy_v1.0.xlsx.
A4: Components (CP-) | B4: Components inherit the criticality of their parent asset by default. Component-level scoring is not defined in Sprint 1.
A5: Types in scope | B5: TY-PUMP-CENT, TY-MOTOR-IM3, TY-COMP-SCREW (as in the hierarchy). Reciprocating compressor is out of scope.
A6: Hierarchy status | B6: DRAFT - the approved hierarchy is a dependency. Re-check IDs once approved.
A7: Example assets | B7: AST-0001 (P-101), AST-0002 (M-101) and AST-0003 (C-101) exist in the hierarchy Asset_Instance sheet. AST-0004, 0007, 0008, 0009, 0010, 0011 and 0012 are ILLUSTRATIVE additions; Group 2 must add real assets to the asset table.
A8: Case severity vs asset criticality | B8: The KB column 'Severity (proposed, unreviewed)' describes the seriousness of a failure case. Asset criticality describes the consequence of losing an asset. Keep them as two separate fields.
A10: asset_id | B10: equipment_tag | C10: class_id | D10: type_id | E10: criticality_index | F10: final_category
A11: AST-0001 | B11: P-101 | C11: EQ-PUMP | D11: TY-PUMP-CENT | E11: =Assessments!M2 -> 62 | F11: =Assessments!S2 -> High
A12: AST-0004 | B12: P-102 | C12: EQ-PUMP | D12: TY-PUMP-CENT | E12: =Assessments!M3 -> 88 | F12: =Assessments!S3 -> Critical
A13: AST-0007 | B13: P-201 | C13: EQ-PUMP | D13: TY-PUMP-CENT | E13: =Assessments!M4 -> 23 | F13: =Assessments!S4 -> Low
A14: AST-0012 | B14: P-305 | C14: EQ-PUMP | D14: TY-PUMP-CENT | E14: =Assessments!M5 -> 64 | F14: =Assessments!S5 -> Critical
A15: AST-0002 | B15: M-101 | C15: EQ-MOTOR | D15: TY-MOTOR-IM3 | E15: =Assessments!M6 -> 62 | F15: =Assessments!S6 -> High
A16: AST-0008 | B16: M-301 | C16: EQ-MOTOR | D16: TY-MOTOR-IM3 | E16: =Assessments!M7 -> 51 | F16: =Assessments!S7 -> Medium
A17: AST-0009 | B17: M-402 | C17: EQ-MOTOR | D17: TY-MOTOR-IM3 | E17: =Assessments!M8 -> 20 | F17: =Assessments!S8 -> Low
A18: AST-0003 | B18: C-101 | C18: EQ-COMP | D18: TY-COMP-SCREW | E18: =Assessments!M9 -> 82 | F18: =Assessments!S9 -> Critical
A19: AST-0010 | B19: C-102 | C19: EQ-COMP | D19: TY-COMP-SCREW | E19: =Assessments!M10 -> 43 | F19: =Assessments!S10 -> Medium
A20: AST-0011 | B20: C-201 | C20: EQ-COMP | D20: TY-COMP-SCREW | E20: =Assessments!M11 -> 32 | F20: =Assessments!S11 -> Low

Sheet Source_Register
A1: source_id | B1: title | C1: publisher / author | D1: edition / year | E1: type | F1: link / identifier | G1: access level (what was actually checked) | H1: what it was used for | I1: limitation | J1: reliability for this use
A2: S01 | B2: ISO 55000:2014 Asset management - Overview, principles and terminology | C2: ISO | D2: 2014 (a revised edition is listed in catalogues; confirm current) | E2: Standard | F2: ISO 55000:2014; catalogue record https://www.dinmedia.de/en/standard/din-iso-55000/271015717 | G2: Catalogue / abstract only | H2: Asset-management context: asset value, risk-informed decisions, asset information. | I2: Context only. No scale or weight is taken from it. | J2: Medium
A3: S02 | B3: IEC 60812 Procedure for failure mode and effects analysis (FMEA) | C3: IEC | D3: Edition to confirm (2006 2nd edition preview seen) | E3: Standard | F3: https://webstore.iec.ch/publication/3571 | G3: Catalogue / contents preview only | H3: Separates failure-mode severity from asset-level criticality. | I3: Context only. Not used for scales. | J3: Medium
A4: S03 | B4: IEC 31010:2019 Risk management - Risk assessment techniques | C4: IEC | D4: 2019 (Edition 2) | E4: Standard | F4: https://webstore.iec.ch/publication/59809 | G4: Catalogue / abstract only | H4: Lists consequence/likelihood matrices and multi-criteria decision analysis among recognised techniques; the weighted score here is a simple multi-criteria approach. | I4: Context only. Technique descriptions were not read. | J4: Medium
A5: S04 | B5: SAE JA1011 Evaluation criteria for reliability-centered maintenance (RCM) processes | C5: SAE International | D5: 1999; revised 2009; a 2024 version is listed | E5: Standard | F5: https://saemobilus.sae.org/content/ja1011_200908/ | G5: Catalogue / abstract only | H5: Context: criticality ranking commonly feeds RCM and maintenance-strategy selection. | I5: Context only. | J5: Medium
A6: S05 | B6: Asset Criticality Ranking: How to Prioritize What Actually Matters | C6: Reliable Plant / Reliabilityweb (practitioner article) | D6: Undated in excerpt | E6: Practitioner article | F6: https://reliamag.com/articles/asset-criticality-ranking-prioritize/ | G6: Partly read (excerpts via web search) | H6: Factor families (safety and environment, production, replaceability), cross-functional scoring, tiers, illustrative numbers. | I6: Used for factor selection and the cross-functional review principle. Its numbers are illustrative and were not adopted. | J6: Medium
A7: S06 | B7: Equipment Criticality Matrix: How to Decide Where Reliability Effort Pays Off | C7: Fabrico (vendor guide) | D7: Undated in excerpt | E7: Vendor guide | F7: https://www.fabrico.io/blog/equipment-criticality-matrix/ | G7: Partly read (excerpts via web search) | H7: Typical dimensions (production, safety, environmental, regulatory, repair cost, replacement lead time); 5 to 7 dimensions; annual review; avoid inflating criticality. | I7: Used for factor list, review frequency and inflation warning. Vendor source: lower weight. | J7: Low
A8: S07 | B8: How to Rank Conveyor Systems Criticality for RCM Programs | C8: OxMaint (vendor guide) | D8: Undated in excerpt | E8: Vendor guide | F8: https://oxmaint.com/blog/post/how-to-rank-conveyor-systems-criticality-for-rcm-programs | G8: Partly read (excerpts via web search) | H8: Example of a weighted 1 to 5 score across consequence dimensions. | I8: Concept only; its weights were NOT adopted. Vendor source: lower weight. | J8: Low
A9: S08 | B9: ISO 14224:2016 Collection and exchange of reliability and maintenance data for equipment | C9: ISO | D9: 2016 | E9: Standard | F9: https://www.iso.org/standard/64076.html | G9: Catalogue only; full text not inspected | H9: Equipment taxonomy context for the hierarchy. | I9: Not used as a source for scoring. M01 to confirm whether any part is relevant to criticality. | J9: Medium
A10: S09 | B10: Operational Sense Industrial Knowledge Base v2.1 | C10: Operational Sense team (internal) | D10: v2.1 | E10: Internal workbook | F10: G1 repository | G10: Read (sheets relevant to severity and lists) | H10: Case-level 'Severity (proposed, unreviewed)' values (Low to Critical); Case Origin wording. | I10: Informs the separation of case severity and asset criticality. Synthetic, pending validation. | J10: Medium
A11: S10 | B11: G1_Equipment_Hierarchy_v1.0.xlsx (M03) | C11: Group 1 / M03 (internal) | D11: v1.0 DRAFT | E11: Internal workbook | F11: G1 repository | G11: Read in full | H11: Class, type and asset IDs used for alignment. | I11: Draft; not yet approved. | J11: Medium
A13: Access-level key: Read in full | Partly read | Catalogue / abstract only | Not verified. Standards were identified from catalogue records; their full text was not purchased or read. Practitioner and vendor sources are secondary and were used for concepts, not for numbers. Replace or supplement with site data and your supervisor's preferred references.

Sheet Review_Log
A1: # | B1: proposed integration requirement | C1: for | D1: status | E1: reviewer name | F1: review date / comments
A2: IR-01 | B2: Store assessments in a separate table linked to the asset instance, not to the type or a case. | C2: Backend | D2: Proposed - review pending
A3: IR-02 | B3: Keep history; allow one current approved assessment per asset (is_current). | C3: Backend | D3: Proposed - review pending
A4: IR-03 | B4: Persist framework_version and weights_version with each assessment so results stay reproducible. | C4: Backend | D4: Proposed - review pending
A5: IR-04 | B5: Calculate weighted_score, criticality_index, band and final category in the database or application; enforce CHECK 1-5 on scores. | C5: Backend | D5: Proposed - review pending
A6: IR-05 | B6: Use lookup tables or enums for category, status and data_origin. | C6: Backend | D6: Proposed - review pending
A7: IR-06 | B7: Expose final_category and criticality_index as filter and ranking metadata for retrieval; keep scores out of the embedding text by default. | C7: AI & Retrieval | D7: Proposed - review pending
A8: IR-07 | B8: Keep case severity (KB) and asset criticality as separate fields. | C8: Backend / AI & Retrieval | D8: Proposed - review pending
A9: IR-08 | B9: Components inherit the parent asset's criticality by default; no component-level scoring in Sprint 1. | C9: Backend | D9: Proposed - review pending
A10: IR-09 | B10: Support CSV import of assessments using the field names on Field_Definitions. | C10: Backend / QA | D10: Proposed - review pending
A11: IR-10 | B11: Capture next_review_date so reassessment triggers can be tracked. | C11: Backend | D11: Proposed - review pending
A13: Sign-off | B13: Role | C13: Name | D13: Date | E13: Outcome
B14: Backend & Database (Group 2) | E14: Pending
B15: AI & Retrieval (Group 3) | E15: Pending
B16: Domain research (M01 / M02) | E16: Pending
B17: QA & Integration (Group 4) | E17: Pending

Sheet Open_Issues
A1: # | B1: area | C1: issue | D1: owner (suggested)
A2: 1 | B2: Approval | C2: Weights, bands, default time bands and override rules are team proposals; approval by the relevant workstreams is pending. | D2: Group 1 lead / supervisor
A3: 2 | B3: Dependency | C3: Approved Industrial Equipment Hierarchy not yet available; framework aligned with the M03 draft. | D3: Group 1 / Group 4
A4: 3 | B4: Calibration | C4: Production and repair time bands are generic defaults; calibrate with a site's production rates and shutdown costs. | D4: Operations input
A5: 4 | B5: Method | C5: Failure likelihood is not scored (consequence-only). Decide whether a likelihood factor or a 5x5 risk matrix is wanted later. | D5: Team decision
A6: 5 | B6: Method | C6: Regulatory exposure is folded into the Safety and Environmental scales. A separate factor is optional. | D6: Team decision
A7: 6 | B7: Data | C7: Example contexts are assumed; asset IDs beyond AST-0003 are illustrative. | D7: M03 / Group 2
A8: 7 | B8: Sensitivity | C8: CRA-0005 and CRA-0008 sit within 2 index points of a band boundary and change category if the Environmental weight rises by 5 points. Review with operations. | D8: Group 1
A9: 8 | B9: Sources | C9: Standards were seen at catalogue level only; confirm current editions (ISO 55000, IEC 60812, SAE JA1011). | D9: M01
A10: 9 | B10: Review | C10: Backend and AI & Retrieval review not yet held. | D10: Group 4 (M12)
